<annotation>
    <filename>20210517-182928.jpg</filename>
    <folder>smd</folder>
    <source>
        <database>smd</database>
        <annotation>custom</annotation>
        <image>custom</image>
    </source>
    <size>
        <width>1280</width>
        <height>720</height>
        <depth>3</depth>
    </size>
    <segmented>0</segmented>
    <object>
        <name>Condensator</name>
        <pose>unspecified</pose>
        <truncated>0</truncated>
        <difficult>0</difficult>
        <bndbox>
            <xmin>922</xmin>
            <ymin>217</ymin>
            <xmax>995</xmax>
            <ymax>276</ymax>
        </bndbox>
    </object>
    <object>
        <name>Diode</name>
        <pose>unspecified</pose>
        <truncated>0</truncated>
        <difficult>0</difficult>
        <bndbox>
            <xmin>778</xmin>
            <ymin>365</ymin>
            <xmax>855</xmax>
            <ymax>425</ymax>
        </bndbox>
    </object>
    <object>
        <name>Resistor</name>
        <pose>unspecified</pose>
        <truncated>0</truncated>
        <difficult>0</difficult>
        <bndbox>
            <xmin>719</xmin>
            <ymin>119</ymin>
            <xmax>790</xmax>
            <ymax>180</ymax>
        </bndbox>
    </object>
</annotation>
