<annotation>
    <filename>20210520-051554.jpg</filename>
    <folder>smd_small</folder>
    <source>
        <database>smd_small</database>
        <annotation>custom</annotation>
        <image>custom</image>
    </source>
    <size>
        <width>1280</width>
        <height>720</height>
        <depth>3</depth>
    </size>
    <segmented>0</segmented>
    <object>
        <name>Condensator</name>
        <pose>unspecified</pose>
        <truncated>0</truncated>
        <difficult>0</difficult>
        <bndbox>
            <xmin>292</xmin>
            <ymin>481</ymin>
            <xmax>376</xmax>
            <ymax>559</ymax>
        </bndbox>
    </object>
</annotation>
